{"chunk_definitions":[{"row":17,"row_count":1,"visible":true,"expansion_state":0,"options":{"engine":"r","label":"unnamed-chunk-4"},"document_id":"342CEC0D","chunk_id":"cv8ceqghr25js","chunk_label":"unnamed-chunk-1"},{"row":28,"row_count":1,"visible":true,"expansion_state":0,"options":{"engine":"r","label":"unnamed-chunk-7"},"document_id":"342CEC0D","chunk_id":"c45f8csz99afe","chunk_label":"unnamed-chunk-2"},{"row":33,"row_count":1,"visible":true,"expansion_state":0,"options":{"engine":"r","label":"unnamed-chunk-6"},"document_id":"342CEC0D","chunk_id":"cendmvvi9b2xy","chunk_label":"unnamed-chunk-3"},{"row":38,"row_count":1,"visible":true,"expansion_state":0,"options":{"engine":"r","label":"unnamed-chunk-8"},"document_id":"342CEC0D","chunk_id":"crnc724ha6b99","chunk_label":"unnamed-chunk-4"},{"row":43,"row_count":1,"visible":true,"expansion_state":0,"options":{"engine":"r","label":"unnamed-chunk-9"},"document_id":"342CEC0D","chunk_id":"c5cogmn45efqi","chunk_label":"unnamed-chunk-5"},{"row":53,"row_count":1,"visible":true,"expansion_state":0,"options":{"engine":"r","label":"unnamed-chunk-10"},"document_id":"342CEC0D","chunk_id":"ciel8xf4bo5hg","chunk_label":"unnamed-chunk-7"},{"row":59,"row_count":1,"visible":true,"expansion_state":0,"options":{"engine":"r","label":"unnamed-chunk-12"},"document_id":"342CEC0D","chunk_id":"cvuiob487qn8p","chunk_label":"unnamed-chunk-8"}],"doc_write_time":1701946646}