{"chunk_definitions":[{"row":28,"row_count":1,"visible":true,"expansion_state":0,"options":{"engine":"r","message":false,"label":"unnamed-chunk-3"},"document_id":"342CEC0D","chunk_id":"cq6zxhdgcu7yp","chunk_label":"unnamed-chunk-2"},{"row":45,"row_count":1,"visible":true,"expansion_state":0,"options":{"engine":"r","results":"hide","label":"unnamed-chunk-3"},"document_id":"342CEC0D","chunk_id":"cge24bqzyd4f7","chunk_label":"unnamed-chunk-3"},{"row":49,"row_count":1,"visible":true,"expansion_state":0,"options":{"engine":"r","label":"unnamed-chunk-4"},"document_id":"342CEC0D","chunk_id":"cjguvr645ak8u","chunk_label":"unnamed-chunk-4"},{"row":183,"row_count":1,"visible":true,"expansion_state":0,"options":{"engine":"r","results":"hide","label":"unnamed-chunk-25"},"document_id":"342CEC0D","chunk_id":"cbh5wdwhrf32j","chunk_label":"unnamed-chunk-8"},{"row":186,"row_count":1,"visible":true,"expansion_state":0,"options":{"engine":"r","label":"unnamed-chunk-26"},"document_id":"342CEC0D","chunk_id":"cv449uhx0p2rj","chunk_label":"unnamed-chunk-9"},{"row":246,"row_count":1,"visible":true,"expansion_state":0,"options":{"engine":"r","label":"unnamed-chunk-16"},"document_id":"342CEC0D","chunk_id":"covpitxwkr42r","chunk_label":"unnamed-chunk-17"},{"row":259,"row_count":1,"visible":true,"expansion_state":0,"options":{"engine":"r","label":"unnamed-chunk-27"},"document_id":"342CEC0D","chunk_id":"cteetyncfe0hx","chunk_label":"unnamed-chunk-18"},{"row":266,"row_count":1,"visible":true,"expansion_state":0,"options":{"engine":"r","label":"unnamed-chunk-28"},"document_id":"342CEC0D","chunk_id":"c9kd4w47f84ot","chunk_label":"unnamed-chunk-19"},{"row":276,"row_count":1,"visible":true,"expansion_state":0,"options":{"engine":"r","label":"unnamed-chunk-1"},"document_id":"342CEC0D","chunk_id":"chlf9sznips9a","chunk_label":"unnamed-chunk-20"}],"doc_write_time":1702853170}